[
  {
    "id": "24d5d6d3-07b8-435d-b49f-890ff1e85136",
    "propertyId": "e4b440e9-5062-4da1-ae25-818dffab8b3b",
    "policyType": "property",
    "policyNumber": "PLY-2026-0001",
    "carrier": "State Farm",
    "agentName": "",
    "agentPhone": "",
    "premiumAnnual": 2400.0,
    "coverageAmount": 500000.0,
    "deductible": 1000.0,
    "effectiveDate": "2026-01-01",
    "expirationDate": "2026-12-31",
    "status": "active",
    "notes": "",
    "metadata": {},
    "createdAt": "2026-03-12 11:50:44",
    "updatedAt": "2026-04-23 00:00:00",
    "enforcementStatus": "fulfilled",
    "leaseRequiresInsurance": true,
    "insuranceRequirement": "Minimum $300K liability + $250K property",
    "activeCoverageVerified": true
  },
  {
    "id": "10d0992d-a673-4e38-8a5c-2fc9e40e1287",
    "propertyId": "e4b440e9-5062-4da1-ae25-818dffab8b3b",
    "policyType": "flood",
    "policyNumber": "FLD-2025",
    "carrier": "FEMA NFIP",
    "agentName": "",
    "agentPhone": "",
    "premiumAnnual": null,
    "coverageAmount": null,
    "deductible": null,
    "effectiveDate": "",
    "expirationDate": "2025-01-01",
    "status": "active",
    "notes": "",
    "metadata": {},
    "createdAt": "2026-03-12 11:51:41",
    "updatedAt": "2026-04-23 00:00:00",
    "enforcementStatus": "lapsed",
    "leaseRequiresInsurance": true,
    "insuranceRequirement": "NFIP flood coverage in flood-zone A",
    "activeCoverageVerified": false
  },
  {
    "id": "appfolio-ins-river-0001",
    "propertyId": "riverwood-club",
    "policyType": "liability",
    "policyNumber": "PLY-RIVER-0001",
    "carrier": "Travelers Insurance",
    "agentName": "",
    "agentPhone": "",
    "premiumAnnual": 4200.0,
    "coverageAmount": 1000000.0,
    "deductible": 2500.0,
    "effectiveDate": "2026-02-01",
    "expirationDate": "2027-02-01",
    "status": "active",
    "notes": "",
    "metadata": {},
    "createdAt": "2026-04-23T00:00:00.000Z",
    "updatedAt": "2026-04-23T00:00:00.000Z",
    "enforcementStatus": "fulfilled",
    "leaseRequiresInsurance": true,
    "insuranceRequirement": "$1M general liability per AppFolio Insurance Enforcement Report schema",
    "activeCoverageVerified": true
  },
  {
    "id": "appfolio-ins-river-0002",
    "propertyId": "riverwood-club",
    "policyType": "property",
    "policyNumber": "PLY-RIVER-0002",
    "carrier": "Liberty Mutual",
    "agentName": "",
    "agentPhone": "",
    "premiumAnnual": 3800.0,
    "coverageAmount": 750000.0,
    "deductible": 1500.0,
    "effectiveDate": "2025-03-15",
    "expirationDate": "2026-03-15",
    "status": "expired",
    "notes": "",
    "metadata": {},
    "createdAt": "2026-04-23T00:00:00.000Z",
    "updatedAt": "2026-04-23T00:00:00.000Z",
    "enforcementStatus": "lapsed",
    "leaseRequiresInsurance": true,
    "insuranceRequirement": "$500K property coverage",
    "activeCoverageVerified": false
  },
  {
    "id": "appfolio-ins-river-0003",
    "propertyId": "riverwood-club",
    "policyType": "umbrella",
    "policyNumber": "PLY-RIVER-0003",
    "carrier": "Chubb",
    "agentName": "",
    "agentPhone": "",
    "premiumAnnual": 1800.0,
    "coverageAmount": 2000000.0,
    "deductible": 0.0,
    "effectiveDate": "2026-01-01",
    "expirationDate": "2027-01-01",
    "status": "active",
    "notes": "",
    "metadata": {},
    "createdAt": "2026-04-23T00:00:00.000Z",
    "updatedAt": "2026-04-23T00:00:00.000Z",
    "enforcementStatus": "required",
    "leaseRequiresInsurance": true,
    "insuranceRequirement": "$2M umbrella coverage (pending verification)",
    "activeCoverageVerified": false
  },
  {
    "id": "appfolio-ins-bv-0001",
    "propertyId": "appfolio-18",
    "policyType": "property",
    "policyNumber": "PLY-BV-0001",
    "carrier": "Farmers Insurance",
    "agentName": "",
    "agentPhone": "",
    "premiumAnnual": 3100.0,
    "coverageAmount": 600000.0,
    "deductible": 2000.0,
    "effectiveDate": "2026-05-20",
    "expirationDate": "2027-05-20",
    "status": "active",
    "notes": "",
    "metadata": {},
    "createdAt": "2026-04-23T00:00:00.000Z",
    "updatedAt": "2026-04-23T00:00:00.000Z",
    "enforcementStatus": "not-required",
    "leaseRequiresInsurance": false,
    "insuranceRequirement": null,
    "activeCoverageVerified": false
  }
]
